shimport/__init__.py
shimport/_version.py
shimport/abcs.py
shimport/constants.py
shimport/hooks.py
shimport/importing.py
shimport/models.py
shimport/module.py
shimport/registry.py
shimport/types.py
shimport/abcs/__init__.py
shimport/abcs/attrdict.py
shimport/util/__init__.py
shimport/util/lme.py
shimport/util/typing.py
shimport-2024.3.12.9.59.dist-info/METADATA
shimport-2024.3.12.9.59.dist-info/WHEEL
shimport-2024.3.12.9.59.dist-info/top_level.txt
shimport-2024.3.12.9.59.dist-info/RECORD
