Metadata-Version: 2.1
Name: shimport
Version: 2024.3.12.9.59
Summary: Import tools for python projects
Home-page: https://github.com/elo-enterprises/shimport/
Author: elo
License: MIT
Project-URL: Documentation, https://github.com/elo-enterprises/shimport/
Project-URL: Source, https://github.com/elo-enterprises/shimport/
Project-URL: Download, https://github.com/elo-enterprises/shimport/#files
Platform: any
Classifier: Programming Language :: Python
Requires-Python: >3.7
Provides-Extra: dev
Requires-Dist: IPython ; extra == 'dev'
Provides-Extra: lint
Requires-Dist: tox ; extra == 'lint'
Provides-Extra: publish
Requires-Dist: twine ; extra == 'publish'
Provides-Extra: testing
Requires-Dist: IPython ; extra == 'testing'
Requires-Dist: tox ; extra == 'testing'
Requires-Dist: pytest ; extra == 'testing'
Requires-Dist: pytest-cov ; extra == 'testing'
Requires-Dist: mock ; extra == 'testing'
Requires-Dist: flake8 ==5.0.4 ; extra == 'testing'
